djassr/__init__.py
djassr/apps.py
djassr/serializers.py
djassr/views.py
djassr-0.3.3.dist-info/DESCRIPTION.rst
djassr-0.3.3.dist-info/METADATA
djassr-0.3.3.dist-info/RECORD
djassr-0.3.3.dist-info/WHEEL
djassr-0.3.3.dist-info/metadata.json
djassr-0.3.3.dist-info/top_level.txt
